redforester/__init__.py
redforester/config.py
redforester-0.1.7.dist-info/LICENSE
redforester-0.1.7.dist-info/METADATA
redforester-0.1.7.dist-info/WHEEL
redforester-0.1.7.dist-info/top_level.txt
redforester-0.1.7.dist-info/RECORD
