Metadata-Version: 2.1
Name: redforester
Version: 0.1.7
Summary: Async RedForester API module for Python 3.7+
Home-page: https://github.com/ichega/redforester
Author: Pavel Katskov
Author-email: pasha_kackov@mail.ru
License: MIT
Platform: UNKNOWN
Classifier: Programming Language :: Python :: 3.7
Classifier: Operating System :: OS Independent
Classifier: License :: OSI Approved :: MIT License
Classifier: Development Status :: 3 - Alpha
Requires-Dist: aiohttp
